kernel_abi_check/__init__.py
kernel_abi_check/__init__.pyi
kernel_abi_check/kernel_abi_check.pypy39-pp73-arm-linux-gnu.so
kernel_abi_check/py.typed
kernel_abi_check-0.12.1.dist-info/METADATA
kernel_abi_check-0.12.1.dist-info/WHEEL
kernel_abi_check-0.12.1.dist-info/RECORD
