Metadata-Version: 2.4
Name: kernel-abi-check
Version: 0.12.1
Classifier: Programming Language :: Rust
Classifier: Programming Language :: Python :: Implementation :: CPython
Summary: Check the ABI of Hub Kernels
Home-Page: https://github.com/huggingface/kernel-builder
Requires-Python: >=3.8
